[{"videoId":"rUWxSEwctFU","thumbnail":{"url":"https://i.ytimg.com/vi/rUWxSEwctFU/mqdefault.jpg","width":320,"height":180},"title":"All over in 10 seconds","channelTitle":"Ian Rushton","channelId":"UC6L6vhzL9yknVr9HxuL-TWg","id":0,"date":"2022-3-29 21:54:04","error":false},{"videoId":"rUWxSEwctFU","thumbnail":{"url":"https://i.ytimg.com/vi/rUWxSEwctFU/mqdefault.jpg","width":320,"height":180},"title":"All over in 10 seconds","channelTitle":"Ian Rushton","channelId":"UC6L6vhzL9yknVr9HxuL-TWg","id":1,"date":"2022-3-29 21:54:28","error":false}]